binary4fun/__init__.py
binary4fun/__main__.py
binary4fun/_version.py
binary4fun/utils/__init__.py
binary4fun/utils/clear_screen.py
binary4fun-0.2.1.dist-info/LICENSE
binary4fun-0.2.1.dist-info/METADATA
binary4fun-0.2.1.dist-info/WHEEL
binary4fun-0.2.1.dist-info/entry_points.txt
binary4fun-0.2.1.dist-info/top_level.txt
binary4fun-0.2.1.dist-info/RECORD
