Metadata-Version: 2.1
Name: binary4fun
Version: 0.2.1
Summary: binary4fun is a small game, which tries to guess a number between 1 and 100 by binary search.
Home-page: https://github.com/moritzkoerber/binary4fun
Author: Moritz Körber
Author-email: moritz.koerber@gmail.com
Keywords: game,binary search
Classifier: License :: OSI Approved :: MIT License
Classifier: Programming Language :: Python
Classifier: Programming Language :: Python :: 3
Requires-Python: >=3
License-File: LICENSE
Provides-Extra: tests
Requires-Dist: pytest ; extra == 'tests'
Requires-Dist: sh ; extra == 'tests'
